README.md
setup.py
mlagents/__init__.py
mlagents/plugins/__init__.py
mlagents/plugins/stats_writer.py
mlagents/torch_utils/__init__.py
mlagents/torch_utils/cpu_utils.py
mlagents/torch_utils/globals.py
mlagents/torch_utils/torch.py
mlagents/trainers/__init__.py
mlagents/trainers/action_info.py
mlagents/trainers/agent_processor.py
mlagents/trainers/behavior_id_utils.py
mlagents/trainers/buffer.py
mlagents/trainers/cli_utils.py
mlagents/trainers/demo_loader.py
mlagents/trainers/directory_utils.py
mlagents/trainers/env_manager.py
mlagents/trainers/environment_parameter_manager.py
mlagents/trainers/exception.py
mlagents/trainers/learn.py
mlagents/trainers/run_experiment.py
mlagents/trainers/settings.py
mlagents/trainers/simple_env_manager.py
mlagents/trainers/stats.py
mlagents/trainers/subprocess_env_manager.py
mlagents/trainers/trainer_controller.py
mlagents/trainers/training_analytics_side_channel.py
mlagents/trainers/training_status.py
mlagents/trainers/trajectory.py
mlagents/trainers/upgrade_config.py
mlagents/trainers/ghost/__init__.py
mlagents/trainers/ghost/controller.py
mlagents/trainers/ghost/trainer.py
mlagents/trainers/model_saver/__init__.py
mlagents/trainers/model_saver/model_saver.py
mlagents/trainers/model_saver/torch_model_saver.py
mlagents/trainers/optimizer/__init__.py
mlagents/trainers/optimizer/optimizer.py
mlagents/trainers/optimizer/torch_optimizer.py
mlagents/trainers/poca/__init__.py
mlagents/trainers/poca/optimizer_torch.py
mlagents/trainers/poca/trainer.py
mlagents/trainers/policy/__init__.py
mlagents/trainers/policy/checkpoint_manager.py
mlagents/trainers/policy/policy.py
mlagents/trainers/policy/torch_policy.py
mlagents/trainers/ppo/__init__.py
mlagents/trainers/ppo/optimizer_torch.py
mlagents/trainers/ppo/trainer.py
mlagents/trainers/sac/__init__.py
mlagents/trainers/sac/optimizer_torch.py
mlagents/trainers/sac/trainer.py
mlagents/trainers/torch/__init__.py
mlagents/trainers/torch/action_flattener.py
mlagents_jf.egg-info/PKG-INFO
mlagents_jf.egg-info/SOURCES.txt
mlagents_jf.egg-info/dependency_links.txt
mlagents_jf.egg-info/entry_points.txt
mlagents_jf.egg-info/not-zip-safe
mlagents_jf.egg-info/requires.txt
mlagents_jf.egg-info/top_level.txt