Metadata-Version: 2.1
Name: mlagents-jf
Version: 0.29.0.dev0
Summary: Unity Machine Learning Agents
Home-page: https://github.com/Unity-Technologies/ml-agents
Author: Unity Technologies
Author-email: ML-Agents@unity3d.com
License: UNKNOWN
Platform: UNKNOWN
Classifier: Intended Audience :: Developers
Classifier: Topic :: Scientific/Engineering :: Artificial Intelligence
Classifier: License :: OSI Approved :: Apache Software License
Classifier: Programming Language :: Python :: 3.6
Classifier: Programming Language :: Python :: 3.7
Classifier: Programming Language :: Python :: 3.8
Requires-Python: >=3.6.1
